sbcm/__init__.py
sbcm/block_calculator.py
sbcm/budget_distortion_analyzer.py
sbcm/config.py
sbcm/sensitivity_analysis.py
sbcm/visualizer.py
standard_block_auditor-0.1.3.dist-info/licenses/LICENSE
standard_block_auditor-0.1.3.dist-info/METADATA
standard_block_auditor-0.1.3.dist-info/WHEEL
standard_block_auditor-0.1.3.dist-info/entry_points.txt
standard_block_auditor-0.1.3.dist-info/top_level.txt
standard_block_auditor-0.1.3.dist-info/RECORD
