Metadata-Version: 2.4
Name: standard-block-auditor
Version: 0.1.3
Summary: A quantitative framework for detecting budgetary distortion.
Author: SBCM Alliance
Project-URL: Homepage, https://github.com/SBCM-Alliance/Standard-Block-Comparison-Method
Project-URL: Repository, https://github.com/SBCM-Alliance/Standard-Block-Comparison-Method
Requires-Python: >=3.7
License-File: LICENSE
Requires-Dist: pandas>=1.3.0
Requires-Dist: matplotlib>=3.4.0
Requires-Dist: numpy>=1.21.0
Requires-Dist: seaborn>=0.11.0
Dynamic: license-file
